macwifi/__init__.py
macwifi/macwifi.py
macwifi-0.0.5.dist-info/METADATA
macwifi-0.0.5.dist-info/WHEEL
macwifi-0.0.5.dist-info/top_level.txt
macwifi-0.0.5.dist-info/RECORD
