Metadata-Version: 2.1
Name: macwifi
Version: 0.0.5
Summary: Macwifi is a Python module that helps you to manage the WiFi on macOS.
Home-page: https://github.com/meowmeowmeowcat/macwifi
Author: meowmeowcat
Author-email: 
Classifier: Programming Language :: Python :: 3
Classifier: Operating System :: MacOS
Requires-Python: >=3.6
